<xml xmlns="http://www.w3.org/1999/xhtml">
  <block type="controls_repeat" id="25" inline="true" x="349" y="100">
    <value name="TIMES">
      <block type="math_number" id="32">
        <field name="NUM">100000</field>
      </block>
    </value>
    <statement name="DO">
      <block type="oled_cleardisplay" id="47">
        <next>
          <block type="oled_setcursor" id="56" inline="true">
            <value name="STARTX">
              <block type="math_number" id="63">
                <field name="NUM">0</field>
              </block>
            </value>
            <value name="STARTY">
              <block type="math_number" id="70">
                <field name="NUM">0</field>
              </block>
            </value>
            <next>
              <block type="oled_drawnumber" id="93" inline="true">
                <value name="NUMBER">
                  <block type="sensor_spectrometer" id="100">
                    <field name="LIGHT">BLUE</field>
                  </block>
                </value>
                <next>
                  <block type="movement_forward" id="110">
                    <next>
                      <block type="controls_if" id="127" inline="false">
                        <mutation else="1"></mutation>
                        <value name="IF0">
                          <block type="logic_compare" id="134" inline="true">
                            <field name="OP">GT</field>
                            <value name="A">
                              <block type="sensor_spectrometer" id="142">
                                <field name="LIGHT">BLUE</field>
                              </block>
                            </value>
                            <value name="B">
                              <block type="math_number" id="149">
                                <field name="NUM">95</field>
                              </block>
                            </value>
                          </block>
                        </value>
                        <statement name="DO0">
                          <block type="movement_stop" id="159"></block>
                        </statement>
                        <statement name="ELSE">
                          <block type="movement_reverse" id="174"></block>
                        </statement>
                      </block>
                    </next>
                  </block>
                </next>
              </block>
            </next>
          </block>
        </next>
      </block>
    </statement>
  </block>
</xml>